odoo/addons/stock_scrap_cancel/README.rst
odoo/addons/stock_scrap_cancel/__init__.py
odoo/addons/stock_scrap_cancel/__manifest__.py
odoo/addons/stock_scrap_cancel/i18n/es.po
odoo/addons/stock_scrap_cancel/i18n/stock_scrap_cancel.pot
odoo/addons/stock_scrap_cancel/models/__init__.py
odoo/addons/stock_scrap_cancel/models/stock_scrap.py
odoo/addons/stock_scrap_cancel/readme/CONTRIBUTORS.rst
odoo/addons/stock_scrap_cancel/readme/DESCRIPTION.rst
odoo/addons/stock_scrap_cancel/readme/USAGE.rst
odoo/addons/stock_scrap_cancel/static/description/icon.png
odoo/addons/stock_scrap_cancel/static/description/index.html
odoo/addons/stock_scrap_cancel/tests/__init__.py
odoo/addons/stock_scrap_cancel/tests/test_stock_scrap_cancel.py
odoo/addons/stock_scrap_cancel/views/stock_scrap_view.xml
odoo13_addon_stock_scrap_cancel-13.0.1.0.1.dev3.dist-info/METADATA
odoo13_addon_stock_scrap_cancel-13.0.1.0.1.dev3.dist-info/WHEEL
odoo13_addon_stock_scrap_cancel-13.0.1.0.1.dev3.dist-info/top_level.txt
odoo13_addon_stock_scrap_cancel-13.0.1.0.1.dev3.dist-info/RECORD
